pasterfu/__init__.py
pasterfu/cli.py
pasterfu/constants.py
pasterfu/fileoperator.py
pasterfu/pasterfu.py
pasterfu/tools.py
pasterfu/tests/__init__.py
pasterfu/tests/test_constants.py
pasterfu/tests/test_pasterfu.py
pasterfu/tests/test_tools.py
pasterfu-0.8.0.dist-info/LICENSE
pasterfu-0.8.0.dist-info/METADATA
pasterfu-0.8.0.dist-info/WHEEL
pasterfu-0.8.0.dist-info/entry_points.txt
pasterfu-0.8.0.dist-info/top_level.txt
pasterfu-0.8.0.dist-info/RECORD
