Metadata-Version: 2.1
Name: pasterfu
Version: 0.8.0
Summary: Open a link with a command read from a database.
Home-page: https://gitlab.com/obtusescholar/pasterfu
Author: obtusescholar
License: GPLv3+
Keywords: paste link url rss
Platform: UNKNOWN
Classifier: Development Status :: 3 - Alpha
Classifier: Environment :: Console
Classifier: License :: OSI Approved :: GNU General Public License v3 or later (GPLv3+)
Classifier: Operating System :: OS Independent
Classifier: Intended Audience :: End Users/Desktop
Classifier: Programming Language :: Python :: 3.7
Classifier: Programming Language :: Python :: 3.8
Classifier: Topic :: Internet
Classifier: Topic :: Terminals
Classifier: Topic :: Utilities
Requires-Python: >=3.9
Requires-Dist: pyperclip
